{"blocks":[{"anchors":[{"direction":"INCOMING","id":"58b48a34-894e-488c-8121-65c0ebfd2b4b","display":"in","parentId":"47a22406-c6da-4b0a-90a0-208bfe7a0155","annotation":"","connectionType":"DATA","hint":"L"},{"direction":"OUTGOING","id":"1566e7a2-8e2a-4461-8b1d-ba597cf47039","display":"out","parentId":"47a22406-c6da-4b0a-90a0-208bfe7a0155","annotation":"","connectionType":"DATA","hint":"R"}],"background":-1,"className":"com.ils.block.Readout","dirty":false,"editorClass":null,"embeddedFontSize":28,"embeddedIcon":"","embeddedLabel":"30.0","iconPath":null,"name":"READOUT-193","nameDisplayed":false,"nameOffsetX":0,"nameOffsetY":0,"originalId":null,"preferredHeight":40,"preferredWidth":100,"properties":[{"editable":true,"type":"STRING","binding":"","bindingType":"NONE","displayed":false,"displayOffsetX":30,"displayOffsetY":50,"name":"Format","value":"%s"},{"editable":false,"type":"STRING","binding":"","bindingType":"ENGINE","displayed":false,"displayOffsetX":30,"displayOffsetY":50,"name":"Value","value":"30.0"}],"receiveEnabled":false,"state":"INITIALIZED","statusText":"","style":"READOUT","subworkspaceId":null,"transmitEnabled":false,"x":186,"y":116,"id":"47a22406-c6da-4b0a-90a0-208bfe7a0155"},{"anchors":[{"direction":"INCOMING","id":"450f1de5-8ac6-46ce-bde7-a915e09ceb21","display":"in","parentId":"edb9e2fd-8add-4062-aad1-b0606c130f2b","annotation":"","connectionType":"DATA","hint":"L"},{"direction":"OUTGOING","id":"918292ae-6d1b-44eb-b24d-b88ea1a50abb","display":"out","parentId":"edb9e2fd-8add-4062-aad1-b0606c130f2b","annotation":"","connectionType":"DATA","hint":"R"}],"background":-1,"className":"com.ils.block.Readout","dirty":false,"editorClass":null,"embeddedFontSize":28,"embeddedIcon":"","embeddedLabel":"FALSE","iconPath":null,"name":"READOUT-884","nameDisplayed":false,"nameOffsetX":0,"nameOffsetY":0,"originalId":null,"preferredHeight":40,"preferredWidth":100,"properties":[{"editable":true,"type":"STRING","binding":"","bindingType":"NONE","displayed":false,"displayOffsetX":30,"displayOffsetY":50,"name":"Format","value":"%s"},{"editable":false,"type":"STRING","binding":"","bindingType":"ENGINE","displayed":false,"displayOffsetX":30,"displayOffsetY":50,"name":"Value","value":"FALSE"}],"receiveEnabled":false,"state":"INITIALIZED","statusText":"","style":"READOUT","subworkspaceId":null,"transmitEnabled":false,"x":370,"y":234,"id":"edb9e2fd-8add-4062-aad1-b0606c130f2b"},{"anchors":[{"direction":"INCOMING","id":"c2bcd1bd-c915-4049-8be6-5068125c3841","display":"in","parentId":"541a3ca0-4260-4700-b59f-6675ae7b924f","annotation":"","connectionType":"DATA","hint":"L"},{"direction":"OUTGOING","id":"d257931a-548c-4b4b-ad32-a63c9a5bdb7d","display":"out","parentId":"541a3ca0-4260-4700-b59f-6675ae7b924f","annotation":"","connectionType":"DATA","hint":"R"}],"background":-986896,"className":"com.ils.block.Bias","dirty":false,"editorClass":null,"embeddedFontSize":36,"embeddedIcon":"","embeddedLabel":"b","iconPath":null,"name":"BIAS-463","nameDisplayed":false,"nameOffsetX":0,"nameOffsetY":0,"originalId":null,"preferredHeight":70,"preferredWidth":70,"properties":[{"editable":true,"type":"DOUBLE","binding":"","bindingType":"NONE","displayed":false,"displayOffsetX":30,"displayOffsetY":50,"name":"Bias","value":1.0}],"receiveEnabled":false,"state":"INITIALIZED","statusText":"","style":"DIAMOND","subworkspaceId":null,"transmitEnabled":false,"x":130,"y":348,"id":"541a3ca0-4260-4700-b59f-6675ae7b924f"},{"anchors":[{"direction":"INCOMING","id":"4a81e963-be13-4e61-8c9b-2dcbcf8ee2dd","display":"x","parentId":"6adca110-0b4b-4c97-aa49-3adb9bc4e720","annotation":"|x|","connectionType":"DATA","hint":"L"},{"direction":"INCOMING","id":"bc6ec1bf-85df-4031-a65f-285ebcbe6f95","display":"y","parentId":"6adca110-0b4b-4c97-aa49-3adb9bc4e720","annotation":"|y|","connectionType":"DATA","hint":"L"},{"direction":"OUTGOING","id":"2db894a2-9379-4c5e-87ae-ae6add8959bf","display":"out","parentId":"6adca110-0b4b-4c97-aa49-3adb9bc4e720","annotation":"","connectionType":"TRUTHVALUE","hint":"R"}],"background":-986896,"className":"com.ils.block.CompareAbsolute","dirty":false,"editorClass":null,"embeddedFontSize":24,"embeddedIcon":"Block/icons/embedded/greater_equal.png","embeddedLabel":"","iconPath":null,"name":"COMPAREABSOLUTE-354","nameDisplayed":false,"nameOffsetX":0,"nameOffsetY":0,"originalId":null,"preferredHeight":60,"preferredWidth":60,"properties":[{"editable":true,"type":"TIME","binding":"","bindingType":"NONE","displayed":false,"displayOffsetX":30,"displayOffsetY":50,"name":"SyncInterval","value":1.0},{"editable":true,"type":"INTEGER","binding":"","bindingType":"NONE","displayed":false,"displayOffsetX":30,"displayOffsetY":50,"name":"Offset","value":0.0}],"receiveEnabled":false,"state":"INITIALIZED","statusText":"","style":"SQUARE","subworkspaceId":null,"transmitEnabled":false,"x":277,"y":225,"id":"6adca110-0b4b-4c97-aa49-3adb9bc4e720"},{"anchors":[{"direction":"OUTGOING","id":"cd68e3b0-3fd1-4b6b-b22c-9d66332ceb65","display":"out","parentId":"80fb9c02-c222-47ac-97b3-b769876dd5a9","annotation":"","connectionType":"DATA","hint":"UNSPECIFIED"}],"background":-16711681,"className":"com.ils.block.Input","dirty":false,"editorClass":null,"embeddedFontSize":24,"embeddedIcon":"","embeddedLabel":"","iconPath":null,"name":"INPUT-548","nameDisplayed":false,"nameOffsetX":0,"nameOffsetY":0,"originalId":null,"preferredHeight":45,"preferredWidth":60,"properties":[{"editable":false,"type":"OBJECT","binding":"","bindingType":"ENGINE","displayed":false,"displayOffsetX":30,"displayOffsetY":50,"name":"Value","value":""},{"editable":true,"type":"OBJECT","binding":"[XOM]MemoryTags/MJKFeed3","bindingType":"TAG_READ","displayed":false,"displayOffsetX":30,"displayOffsetY":50,"name":"TagPath","value":""}],"receiveEnabled":false,"state":"INITIALIZED","statusText":"","style":"ARROW","subworkspaceId":null,"transmitEnabled":false,"x":48,"y":223,"id":"80fb9c02-c222-47ac-97b3-b769876dd5a9"}],"connections":[{"beginBlock":"80fb9c02-c222-47ac-97b3-b769876dd5a9","endBlock":"47a22406-c6da-4b0a-90a0-208bfe7a0155","beginAnchor":{"direction":"OUTGOING","id":"out","parentId":"80fb9c02-c222-47ac-97b3-b769876dd5a9","anchorX":54,"anchorY":21,"pathLeaderX":70,"pathLeaderY":21,"hotSpotX":48,"hotSpotY":15,"hotSpotHeight":15,"hotSpotWidth":12},"endAnchor":{"direction":"INCOMING","id":"in","parentId":"47a22406-c6da-4b0a-90a0-208bfe7a0155","anchorX":0,"anchorY":20,"pathLeaderX":-10,"pathLeaderY":20,"hotSpotX":0,"hotSpotY":11,"hotSpotHeight":18,"hotSpotWidth":18},"type":"DATA"},{"beginBlock":"80fb9c02-c222-47ac-97b3-b769876dd5a9","endBlock":"6adca110-0b4b-4c97-aa49-3adb9bc4e720","beginAnchor":{"direction":"OUTGOING","id":"out","parentId":"80fb9c02-c222-47ac-97b3-b769876dd5a9","anchorX":54,"anchorY":21,"pathLeaderX":70,"pathLeaderY":21,"hotSpotX":48,"hotSpotY":15,"hotSpotHeight":15,"hotSpotWidth":12},"endAnchor":{"direction":"INCOMING","id":"x","parentId":"6adca110-0b4b-4c97-aa49-3adb9bc4e720","anchorX":0,"anchorY":19,"pathLeaderX":-10,"pathLeaderY":19,"hotSpotX":0,"hotSpotY":10,"hotSpotHeight":18,"hotSpotWidth":18},"type":"DATA"},{"beginBlock":"80fb9c02-c222-47ac-97b3-b769876dd5a9","endBlock":"541a3ca0-4260-4700-b59f-6675ae7b924f","beginAnchor":{"direction":"OUTGOING","id":"out","parentId":"80fb9c02-c222-47ac-97b3-b769876dd5a9","anchorX":54,"anchorY":21,"pathLeaderX":70,"pathLeaderY":21,"hotSpotX":48,"hotSpotY":15,"hotSpotHeight":15,"hotSpotWidth":12},"endAnchor":{"direction":"INCOMING","id":"in","parentId":"541a3ca0-4260-4700-b59f-6675ae7b924f","anchorX":0,"anchorY":35,"pathLeaderX":-10,"pathLeaderY":35,"hotSpotX":0,"hotSpotY":26,"hotSpotHeight":18,"hotSpotWidth":18},"type":"DATA"},{"beginBlock":"541a3ca0-4260-4700-b59f-6675ae7b924f","endBlock":"6adca110-0b4b-4c97-aa49-3adb9bc4e720","beginAnchor":{"direction":"OUTGOING","id":"out","parentId":"541a3ca0-4260-4700-b59f-6675ae7b924f","anchorX":70,"anchorY":34,"pathLeaderX":80,"pathLeaderY":34,"hotSpotX":52,"hotSpotY":26,"hotSpotHeight":17,"hotSpotWidth":18},"endAnchor":{"direction":"INCOMING","id":"y","parentId":"6adca110-0b4b-4c97-aa49-3adb9bc4e720","anchorX":0,"anchorY":40,"pathLeaderX":-10,"pathLeaderY":40,"hotSpotX":0,"hotSpotY":31,"hotSpotHeight":18,"hotSpotWidth":18},"type":"DATA"},{"beginBlock":"6adca110-0b4b-4c97-aa49-3adb9bc4e720","endBlock":"edb9e2fd-8add-4062-aad1-b0606c130f2b","beginAnchor":{"direction":"OUTGOING","id":"out","parentId":"6adca110-0b4b-4c97-aa49-3adb9bc4e720","anchorX":60,"anchorY":29,"pathLeaderX":70,"pathLeaderY":29,"hotSpotX":42,"hotSpotY":21,"hotSpotHeight":17,"hotSpotWidth":18},"endAnchor":{"direction":"INCOMING","id":"in","parentId":"edb9e2fd-8add-4062-aad1-b0606c130f2b","anchorX":0,"anchorY":20,"pathLeaderX":-10,"pathLeaderY":20,"hotSpotX":0,"hotSpotY":11,"hotSpotHeight":18,"hotSpotWidth":18},"type":"TRUTHVALUE"}],"id":"42d063ff-dff1-4d47-a215-c56c3aa920d5","name":"ASimpleGuy1","resourceId":470,"state":"ACTIVE","dirty":false,"encapsulationBlockId":null}